mini_project/__init__.py
mini_project/main.py
HimpunanTEAM6-1.0.0.dist-info/METADATA
HimpunanTEAM6-1.0.0.dist-info/WHEEL
HimpunanTEAM6-1.0.0.dist-info/top_level.txt
HimpunanTEAM6-1.0.0.dist-info/RECORD
