Metadata-Version: 2.1
Name: HimpunanTEAM6
Version: 1.0.0
Summary: Package Python untuk operasi himpunan menggunakan teori himpunan dasar
Home-page: https://github.com/leowdij08/Team-6_Diskrit_Himpunan.git
Author: Team 6_Leonard_Apryadi_Alfian
Author-email: leowidj@gmail.com
Classifier: Programming Language :: Python :: 3
Classifier: License :: OSI Approved :: MIT License
Classifier: Operating System :: OS Independent
Requires-Python: >=3.6
